CHANGELOG.md
LICENSE
fastx_barber/__init__.py
fastx_barber/bedio.py
fastx_barber/const.py
fastx_barber/exception.py
fastx_barber/flag.py
fastx_barber/io.py
fastx_barber/match.py
fastx_barber/qual.py
fastx_barber/random.py
fastx_barber/scriptio.py
fastx_barber/scripts/__init__.py
fastx_barber/scripts/arguments.py
fastx_barber/scripts/barber.py
fastx_barber/scripts/find_seq.py
fastx_barber/scripts/flag.py
fastx_barber/scripts/flag_extract.py
fastx_barber/scripts/flag_filter.py
fastx_barber/scripts/flag_regex.py
fastx_barber/scripts/flag_split.py
fastx_barber/scripts/flag_stats.py
fastx_barber/scripts/match.py
fastx_barber/scripts/trim.py
fastx_barber/scripts/trim_len.py
fastx_barber/scripts/trim_qual.py
fastx_barber/scripts/trim_regex.py
fastx_barber/seqio.py
fastx_barber/tests/test_bedio.py
fastx_barber/tests/test_flag.py
fastx_barber/tests/test_io.py
fastx_barber/tests/test_match.py
fastx_barber/tests/test_qual.py
fastx_barber/tests/test_random.py
fastx_barber/tests/test_seqio.py
fastx_barber/tests/test_trim.py
fastx_barber/trim.py
fastx_barber-0.1.5.dist-info/entry_points.txt
fastx_barber-0.1.5.dist-info/LICENSE
fastx_barber-0.1.5.dist-info/WHEEL
fastx_barber-0.1.5.dist-info/METADATA
fastx_barber-0.1.5.dist-info/RECORD
