Metadata-Version: 2.1
Name: fastx-barber
Version: 0.1.5
Summary: FASTX trimming tools
Home-page: https://github.com/ggirelli/fastx-barber
License: MIT
Keywords: fasta,fastq,trimming,bioinformatics
Author: Gabriele Girelli
Author-email: gigi.ga90@gmail.com
Requires-Python: >=3.8,<4.0
Classifier: Development Status :: 4 - Beta
Classifier: Environment :: Console
Classifier: Intended Audience :: Science/Research
Classifier: License :: OSI Approved :: MIT License
Classifier: Operating System :: POSIX :: Linux
Classifier: Operating System :: Unix
Classifier: Programming Language :: Python :: 3
Classifier: Programming Language :: Python :: 3.8
Classifier: Programming Language :: Python :: 3.9
Classifier: Topic :: Scientific/Engineering :: Bio-Informatics
Requires-Dist: biopython (>=1.77,<2.0)
Requires-Dist: joblib (>=0.16,<1.1)
Requires-Dist: numpy (>=1.19.1,<2.0.0)
Requires-Dist: pandas (>=1.1.2,<2.0.0)
Requires-Dist: pytest (>=6.1.1,<7.0.0)
Requires-Dist: regex (>=2020.7.14,<2022.0.0)
Requires-Dist: rich (>=9,<11)
Requires-Dist: tqdm (>=4.48.1,<5.0.0)
Project-URL: Repository, https://github.com/ggirelli/fastx-barber
